picidae/__init__.py
picidae-1.0.6.dist-info/LICENSE
picidae-1.0.6.dist-info/METADATA
picidae-1.0.6.dist-info/WHEEL
picidae-1.0.6.dist-info/top_level.txt
picidae-1.0.6.dist-info/RECORD
